{"id": "a3e4a1c9-db14-11eb-971e-acd1b8e343fc", "name": "hungry_geese", "title": "Hungry Geese", "description": "Similar to the classic snake game with multiple players", "version": "1.0.0", "configuration": {"episodeSteps": 200, "actTimeout": 1, "runTimeout": 1200, "columns": 11, "rows": 7, "hunger_rate": 40, "min_food": 2, "max_length": 99}, "specification": {"action": {"description": "Direction to move the head of your players goose.", "type": "string", "enum": ["NORTH", "EAST", "SOUTH", "WEST"], "default": "NORTH"}, "agents": [1, 2, 3, 4, 5, 6, 7, 8], "configuration": {"episodeSteps": {"description": "Maximum number of steps in the episode.", "type": "integer", "minimum": 1, "default": 200}, "actTimeout": {"description": "Maximum runtime (seconds) to obtain an action from an agent.", "type": "number", "minimum": 0, "default": 1}, "runTimeout": {"description": "Maximum runtime (seconds) of an episode (not necessarily DONE).", "type": "number", "minimum": 0, "default": 1200}, "columns": {"description": "Horizontal number of cells on the board.", "type": "integer", "default": 11, "minimum": 3}, "rows": {"description": "Vertical number of cells on the board.", "type": "integer", "default": 7, "minimum": 3}, "hunger_rate": {"description": "The number of steps before the goose shrinks a cell.", "type": "integer", "minimum": 1, "default": 40}, "min_food": {"description": "The minimum amount of food present for all steps.", "type": "integer", "default": 2, "minimum": 1}, "max_length": {"description": "The max length any goose can be. Total reward = (max length + 1) * steps survived + goose length.", "type": "integer", "default": 99}}, "info": {}, "observation": {"remainingOverageTime": {"description": "Total remaining banked time (seconds) that can be used in excess of per-step actTimeouts -- agent is disqualified with TIMEOUT status when this drops below 0.", "shared": false, "type": "number", "minimum": 0, "default": 60}, "step": {"description": "Current step within the episode.", "type": "integer", "shared": true, "minimum": 0, "default": 0}, "geese": {"description": "List of geese in order by the agent index.", "type": "array", "default": [], "shared": true}, "food": {"description": "Positions on the board where food is present.", "type": "array", "default": [], "shared": true}, "index": {"description": "Index of the current agent's goose in the list of geese.", "type": "integer", "minimum": 0, "defaults": [0, 1, 2, 3, 4, 5, 6, 7]}}, "reward": {"description": "steps survived * (max goose length + 1) + current goose length.", "type": ["number", "null"], "default": 0, "minimum": 0}}, "steps": [[{"action": "NORTH", "reward": 0, "info": {}, "observation": {"remainingOverageTime": 60, "step": 0, "geese": [[27], [66]], "food": [47, 37], "index": 0}, "status": "ACTIVE"}, {"action": "NORTH", "reward": 0, "info": {}, "observation": {"remainingOverageTime": 60, "index": 1}, "status": "ACTIVE"}], [{"action": "NORTH", "reward": 201, "info": {}, "observation": {"remainingOverageTime": 60, "step": 1, "geese": [[16], [67]], "food": [47, 37], "index": 0}, "status": "ACTIVE"}, {"action": "EAST", "reward": 201, "info": {}, "observation": {"remainingOverageTime": 60, "index": 1}, "status": "ACTIVE"}], [{"action": "WEST", "reward": 301, "info": {}, "observation": {"remainingOverageTime": 60, "step": 2, "geese": [[15], [68]], "food": [47, 37], "index": 0}, "status": "ACTIVE"}, {"action": "EAST", "reward": 301, "info": {}, "observation": {"remainingOverageTime": 60, "index": 1}, "status": "ACTIVE"}], [{"action": "SOUTH", "reward": 401, "info": {}, "observation": {"remainingOverageTime": 60, "step": 3, "geese": [[26], [69]], "food": [47, 37], "index": 0}, "status": "ACTIVE"}, {"action": "EAST", "reward": 401, "info": {}, "observation": {"remainingOverageTime": 60, "index": 1}, "status": "ACTIVE"}], [{"action": "SOUTH", "reward": 502, "info": {}, "observation": {"remainingOverageTime": 60, "step": 4, "geese": [[37, 26], [58]], "food": [47, 31], "index": 0}, "status": "ACTIVE"}, {"action": "NORTH", "reward": 501, "info": {}, "observation": {"remainingOverageTime": 60, "index": 1}, "status": "ACTIVE"}], [{"action": "EAST", "reward": 602, "info": {}, "observation": {"remainingOverageTime": 60, "step": 5, "geese": [[38, 37], [47, 58]], "food": [31, 22], "index": 0}, "status": "ACTIVE"}, {"action": "NORTH", "reward": 602, "info": {}, "observation": {"remainingOverageTime": 60, "index": 1}, "status": "ACTIVE"}], [{"action": "EAST", "reward": 702, "info": {}, "observation": {"remainingOverageTime": 60, "step": 6, "geese": [[39, 38], [36, 47]], "food": [31, 22], "index": 0}, "status": "ACTIVE"}, {"action": "NORTH", "reward": 702, "info": {}, "observation": {"remainingOverageTime": 60, "index": 1}, "status": "ACTIVE"}], [{"action": "EAST", "reward": 802, "info": {}, "observation": {"remainingOverageTime": 60, "step": 7, "geese": [[40, 39], [25, 36]], "food": [31, 22], "index": 0}, "status": "ACTIVE"}, {"action": "NORTH", "reward": 802, "info": {}, "observation": {"remainingOverageTime": 60, "index": 1}, "status": "ACTIVE"}], [{"action": "EAST", "reward": 902, "info": {}, "observation": {"remainingOverageTime": 60, "step": 8, "geese": [[41, 40], [24, 25]], "food": [31, 22], "index": 0}, "status": "ACTIVE"}, {"action": "WEST", "reward": 902, "info": {}, "observation": {"remainingOverageTime": 60, "index": 1}, "status": "ACTIVE"}], [{"action": "EAST", "reward": 1002, "info": {}, "observation": {"remainingOverageTime": 60, "step": 9, "geese": [[42, 41], [23, 24]], "food": [31, 22], "index": 0}, "status": "ACTIVE"}, {"action": "WEST", "reward": 1002, "info": {}, "observation": {"remainingOverageTime": 60, "index": 1}, "status": "ACTIVE"}], [{"action": "NORTH", "reward": 1103, "info": {}, "observation": {"remainingOverageTime": 60, "step": 10, "geese": [[31, 42, 41], [22, 23, 24]], "food": [59, 10], "index": 0}, "status": "ACTIVE"}, {"action": "WEST", "reward": 1103, "info": {}, "observation": {"remainingOverageTime": 60, "index": 1}, "status": "ACTIVE"}], [{"action": "NORTH", "reward": 1203, "info": {}, "observation": {"remainingOverageTime": 60, "step": 11, "geese": [[20, 31, 42], [11, 22, 23]], "food": [59, 10], "index": 0}, "status": "ACTIVE"}, {"action": "NORTH", "reward": 1203, "info": {}, "observation": {"remainingOverageTime": 60, "index": 1}, "status": "ACTIVE"}], [{"action": "NORTH", "reward": 1303, "info": {}, "observation": {"remainingOverageTime": 60, "step": 12, "geese": [[9, 20, 31], [0, 11, 22]], "food": [59, 10], "index": 0}, "status": "ACTIVE"}, {"action": "NORTH", "reward": 1303, "info": {}, "observation": {"remainingOverageTime": 60, "index": 1}, "status": "ACTIVE"}], [{"action": "EAST", "reward": 1404, "info": {}, "observation": {"remainingOverageTime": 60, "step": 13, "geese": [[10, 9, 20, 31], [1, 0, 11]], "food": [59, 39], "index": 0}, "status": "ACTIVE"}, {"action": "EAST", "reward": 1403, "info": {}, "observation": {"remainingOverageTime": 60, "index": 1}, "status": "ACTIVE"}], [{"action": "NORTH", "reward": 1504, "info": {}, "observation": {"remainingOverageTime": 60, "step": 14, "geese": [[76, 10, 9, 20], [2, 1, 0]], "food": [59, 39], "index": 0}, "status": "ACTIVE"}, {"action": "EAST", "reward": 1503, "info": {}, "observation": {"remainingOverageTime": 60, "index": 1}, "status": "ACTIVE"}], [{"action": "NORTH", "reward": 1604, "info": {}, "observation": {"remainingOverageTime": 60, "step": 15, "geese": [[65, 76, 10, 9], [3, 2, 1]], "food": [59, 39], "index": 0}, "status": "ACTIVE"}, {"action": "EAST", "reward": 1603, "info": {}, "observation": {"remainingOverageTime": 60, "index": 1}, "status": "ACTIVE"}], [{"action": "WEST", "reward": 1704, "info": {}, "observation": {"remainingOverageTime": 60, "step": 16, "geese": [[64, 65, 76, 10], [4, 3, 2]], "food": [59, 39], "index": 0}, "status": "ACTIVE"}, {"action": "EAST", "reward": 1703, "info": {}, "observation": {"remainingOverageTime": 60, "index": 1}, "status": "ACTIVE"}], [{"action": "WEST", "reward": 1804, "info": {}, "observation": {"remainingOverageTime": 60, "step": 17, "geese": [[63, 64, 65, 76], [70, 4, 3]], "food": [59, 39], "index": 0}, "status": "ACTIVE"}, {"action": "NORTH", "reward": 1803, "info": {}, "observation": {"remainingOverageTime": 60, "index": 1}, "status": "ACTIVE"}], [{"action": "WEST", "reward": 1904, "info": {}, "observation": {"remainingOverageTime": 60, "step": 18, "geese": [[62, 63, 64, 65], [59, 70, 4, 3]], "food": [39, 28], "index": 0}, "status": "ACTIVE"}, {"action": "NORTH", "reward": 1904, "info": {}, "observation": {"remainingOverageTime": 60, "index": 1}, "status": "ACTIVE"}], [{"action": "WEST", "reward": 2004, "info": {}, "observation": {"remainingOverageTime": 60, "step": 19, "geese": [[61, 62, 63, 64], [60, 59, 70, 4]], "food": [39, 28], "index": 0}, "status": "ACTIVE"}, {"action": "EAST", "reward": 2004, "info": {}, "observation": {"remainingOverageTime": 60, "index": 1}, "status": "ACTIVE"}], [{"action": "NORTH", "reward": 2104, "info": {}, "observation": {"remainingOverageTime": 60, "step": 20, "geese": [[50, 61, 62, 63], [49, 60, 59, 70]], "food": [39, 28], "index": 0}, "status": "ACTIVE"}, {"action": "NORTH", "reward": 2104, "info": {}, "observation": {"remainingOverageTime": 60, "index": 1}, "status": "ACTIVE"}], [{"action": "NORTH", "reward": 2205, "info": {}, "observation": {"remainingOverageTime": 60, "step": 21, "geese": [[39, 50, 61, 62, 63], [38, 49, 60, 59]], "food": [28, 22], "index": 0}, "status": "ACTIVE"}, {"action": "NORTH", "reward": 2204, "info": {}, "observation": {"remainingOverageTime": 60, "index": 1}, "status": "ACTIVE"}], [{"action": "NORTH", "reward": 2306, "info": {}, "observation": {"remainingOverageTime": 60, "step": 22, "geese": [[28, 39, 50, 61, 62, 63], [27, 38, 49, 60]], "food": [22, 6], "index": 0}, "status": "ACTIVE"}, {"action": "NORTH", "reward": 2304, "info": {}, "observation": {"remainingOverageTime": 60, "index": 1}, "status": "ACTIVE"}], [{"action": "NORTH", "reward": 2406, "info": {}, "observation": {"remainingOverageTime": 60, "step": 23, "geese": [[17, 28, 39, 50, 61, 62], [16, 27, 38, 49]], "food": [22, 6], "index": 0}, "status": "ACTIVE"}, {"action": "NORTH", "reward": 2404, "info": {}, "observation": {"remainingOverageTime": 60, "index": 1}, "status": "ACTIVE"}], [{"action": "NORTH", "reward": 2507, "info": {}, "observation": {"remainingOverageTime": 60, "step": 24, "geese": [[6, 17, 28, 39, 50, 61, 62], [15, 16, 27, 38]], "food": [22, 53], "index": 0}, "status": "ACTIVE"}, {"action": "WEST", "reward": 2504, "info": {}, "observation": {"remainingOverageTime": 60, "index": 1}, "status": "ACTIVE"}], [{"action": "NORTH", "reward": 2607, "info": {}, "observation": {"remainingOverageTime": 60, "step": 25, "geese": [[72, 6, 17, 28, 39, 50, 61], [14, 15, 16, 27]], "food": [22, 53], "index": 0}, "status": "ACTIVE"}, {"action": "WEST", "reward": 2604, "info": {}, "observation": {"remainingOverageTime": 60, "index": 1}, "status": "ACTIVE"}], [{"action": "NORTH", "reward": 2707, "info": {}, "observation": {"remainingOverageTime": 60, "step": 26, "geese": [[61, 72, 6, 17, 28, 39, 50], [13, 14, 15, 16]], "food": [22, 53], "index": 0}, "status": "ACTIVE"}, {"action": "WEST", "reward": 2704, "info": {}, "observation": {"remainingOverageTime": 60, "index": 1}, "status": "ACTIVE"}], [{"action": "NORTH", "reward": 2807, "info": {}, "observation": {"remainingOverageTime": 60, "step": 27, "geese": [[50, 61, 72, 6, 17, 28, 39], [12, 13, 14, 15]], "food": [22, 53], "index": 0}, "status": "ACTIVE"}, {"action": "WEST", "reward": 2804, "info": {}, "observation": {"remainingOverageTime": 60, "index": 1}, "status": "ACTIVE"}], [{"action": "EAST", "reward": 2907, "info": {}, "observation": {"remainingOverageTime": 60, "step": 28, "geese": [[51, 50, 61, 72, 6, 17, 28], [11, 12, 13, 14]], "food": [22, 53], "index": 0}, "status": "ACTIVE"}, {"action": "WEST", "reward": 2904, "info": {}, "observation": {"remainingOverageTime": 60, "index": 1}, "status": "ACTIVE"}], [{"action": "EAST", "reward": 3007, "info": {}, "observation": {"remainingOverageTime": 60, "step": 29, "geese": [[52, 51, 50, 61, 72, 6, 17], [22, 11, 12, 13, 14]], "food": [53, 74], "index": 0}, "status": "ACTIVE"}, {"action": "SOUTH", "reward": 3005, "info": {}, "observation": {"remainingOverageTime": 60, "index": 1}, "status": "ACTIVE"}], [{"action": "EAST", "reward": 3108, "info": {}, "observation": {"remainingOverageTime": 60, "step": 30, "geese": [[53, 52, 51, 50, 61, 72, 6, 17], [32, 22, 11, 12, 13]], "food": [74, 20], "index": 0}, "status": "ACTIVE"}, {"action": "WEST", "reward": 3105, "info": {}, "observation": {"remainingOverageTime": 60, "index": 1}, "status": "ACTIVE"}], [{"action": "SOUTH", "reward": 3208, "info": {}, "observation": {"remainingOverageTime": 60, "step": 31, "geese": [[64, 53, 52, 51, 50, 61, 72, 6], [21, 32, 22, 11, 12]], "food": [74, 20], "index": 0}, "status": "ACTIVE"}, {"action": "NORTH", "reward": 3205, "info": {}, "observation": {"remainingOverageTime": 60, "index": 1}, "status": "ACTIVE"}], [{"action": "SOUTH", "reward": 3308, "info": {}, "observation": {"remainingOverageTime": 60, "step": 32, "geese": [[75, 64, 53, 52, 51, 50, 61, 72], [20, 21, 32, 22, 11, 12]], "food": [74, 43], "index": 0}, "status": "ACTIVE"}, {"action": "WEST", "reward": 3306, "info": {}, "observation": {"remainingOverageTime": 60, "index": 1}, "status": "ACTIVE"}], [{"action": "WEST", "reward": 3409, "info": {}, "observation": {"remainingOverageTime": 60, "step": 33, "geese": [[74, 75, 64, 53, 52, 51, 50, 61, 72], [31, 20, 21, 32, 22, 11]], "food": [43, 40], "index": 0}, "status": "ACTIVE"}, {"action": "SOUTH", "reward": 3406, "info": {}, "observation": {"remainingOverageTime": 60, "index": 1}, "status": "ACTIVE"}], [{"action": "SOUTH", "reward": 3509, "info": {}, "observation": {"remainingOverageTime": 60, "step": 34, "geese": [[8, 74, 75, 64, 53, 52, 51, 50, 61], [42, 31, 20, 21, 32, 22]], "food": [43, 40], "index": 0}, "status": "ACTIVE"}, {"action": "SOUTH", "reward": 3506, "info": {}, "observation": {"remainingOverageTime": 60, "index": 1}, "status": "ACTIVE"}], [{"action": "SOUTH", "reward": 3609, "info": {}, "observation": {"remainingOverageTime": 60, "step": 35, "geese": [[19, 8, 74, 75, 64, 53, 52, 51, 50], [43, 42, 31, 20, 21, 32, 22]], "food": [40, 57], "index": 0}, "status": "ACTIVE"}, {"action": "EAST", "reward": 3607, "info": {}, "observation": {"remainingOverageTime": 60, "index": 1}, "status": "ACTIVE"}], [{"action": "SOUTH", "reward": 3709, "info": {}, "observation": {"remainingOverageTime": 60, "step": 36, "geese": [[30, 19, 8, 74, 75, 64, 53, 52, 51], [33, 43, 42, 31, 20, 21, 32]], "food": [40, 57], "index": 0}, "status": "ACTIVE"}, {"action": "EAST", "reward": 3707, "info": {}, "observation": {"remainingOverageTime": 60, "index": 1}, "status": "ACTIVE"}], [{"action": "SOUTH", "reward": 3809, "info": {}, "observation": {"remainingOverageTime": 60, "step": 37, "geese": [[41, 30, 19, 8, 74, 75, 64, 53, 52], [34, 33, 43, 42, 31, 20, 21]], "food": [40, 57], "index": 0}, "status": "ACTIVE"}, {"action": "EAST", "reward": 3807, "info": {}, "observation": {"remainingOverageTime": 60, "index": 1}, "status": "ACTIVE"}], [{"action": "WEST", "reward": 3910, "info": {}, "observation": {"remainingOverageTime": 60, "step": 38, "geese": [[40, 41, 30, 19, 8, 74, 75, 64, 53, 52], [35, 34, 33, 43, 42, 31, 20]], "food": [57, 11], "index": 0}, "status": "ACTIVE"}, {"action": "EAST", "reward": 3907, "info": {}, "observation": {"remainingOverageTime": 60, "index": 1}, "status": "ACTIVE"}], [{"action": "WEST", "reward": 4010, "info": {}, "observation": {"remainingOverageTime": 60, "step": 39, "geese": [[39, 40, 41, 30, 19, 8, 74, 75, 64, 53], [46, 35, 34, 33, 43, 42, 31]], "food": [57, 11], "index": 0}, "status": "ACTIVE"}, {"action": "SOUTH", "reward": 4007, "info": {}, "observation": {"remainingOverageTime": 60, "index": 1}, "status": "ACTIVE"}], [{"action": "WEST", "reward": 4109, "info": {}, "observation": {"remainingOverageTime": 60, "step": 40, "geese": [[38, 39, 40, 41, 30, 19, 8, 74, 75], [57, 46, 35, 34, 33, 43, 42]], "food": [11, 56], "index": 0}, "status": "ACTIVE"}, {"action": "SOUTH", "reward": 4107, "info": {}, "observation": {"remainingOverageTime": 60, "index": 1}, "status": "ACTIVE"}], [{"action": "WEST", "reward": 4209, "info": {}, "observation": {"remainingOverageTime": 60, "step": 41, "geese": [[37, 38, 39, 40, 41, 30, 19, 8, 74], [56, 57, 46, 35, 34, 33, 43, 42]], "food": [11, 10], "index": 0}, "status": "ACTIVE"}, {"action": "WEST", "reward": 4208, "info": {}, "observation": {"remainingOverageTime": 60, "index": 1}, "status": "ACTIVE"}], [{"action": "WEST", "reward": 4309, "info": {}, "observation": {"remainingOverageTime": 60, "step": 42, "geese": [[36, 37, 38, 39, 40, 41, 30, 19, 8], [55, 56, 57, 46, 35, 34, 33, 43]], "food": [11, 10], "index": 0}, "status": "ACTIVE"}, {"action": "WEST", "reward": 4308, "info": {}, "observation": {"remainingOverageTime": 60, "index": 1}, "status": "ACTIVE"}], [{"action": "NORTH", "reward": 4409, "info": {}, "observation": {"remainingOverageTime": 60, "step": 43, "geese": [[25, 36, 37, 38, 39, 40, 41, 30, 19], [65, 55, 56, 57, 46, 35, 34, 33]], "food": [11, 10], "index": 0}, "status": "ACTIVE"}, {"action": "WEST", "reward": 4408, "info": {}, "observation": {"remainingOverageTime": 60, "index": 1}, "status": "ACTIVE"}], [{"action": "WEST", "reward": 4509, "info": {}, "observation": {"remainingOverageTime": 60, "step": 44, "geese": [[24, 25, 36, 37, 38, 39, 40, 41, 30], [76, 65, 55, 56, 57, 46, 35, 34]], "food": [11, 10], "index": 0}, "status": "ACTIVE"}, {"action": "SOUTH", "reward": 4508, "info": {}, "observation": {"remainingOverageTime": 60, "index": 1}, "status": "ACTIVE"}], [{"action": "WEST", "reward": 4609, "info": {}, "observation": {"remainingOverageTime": 60, "step": 45, "geese": [[23, 24, 25, 36, 37, 38, 39, 40, 41], [10, 76, 65, 55, 56, 57, 46, 35, 34]], "food": [11, 75], "index": 0}, "status": "ACTIVE"}, {"action": "SOUTH", "reward": 4609, "info": {}, "observation": {"remainingOverageTime": 60, "index": 1}, "status": "ACTIVE"}], [{"action": "WEST", "reward": 4709, "info": {}, "observation": {"remainingOverageTime": 60, "step": 46, "geese": [[22, 23, 24, 25, 36, 37, 38, 39, 40], [0, 10, 76, 65, 55, 56, 57, 46, 35]], "food": [11, 75], "index": 0}, "status": "ACTIVE"}, {"action": "EAST", "reward": 4709, "info": {}, "observation": {"remainingOverageTime": 60, "index": 1}, "status": "ACTIVE"}], [{"action": "NORTH", "reward": 4810, "info": {}, "observation": {"remainingOverageTime": 60, "step": 47, "geese": [[11, 22, 23, 24, 25, 36, 37, 38, 39, 40], [1, 0, 10, 76, 65, 55, 56, 57, 46]], "food": [75, 73], "index": 0}, "status": "ACTIVE"}, {"action": "EAST", "reward": 4809, "info": {}, "observation": {"remainingOverageTime": 60, "index": 1}, "status": "ACTIVE"}], [{"action": "WEST", "reward": 4910, "info": {}, "observation": {"remainingOverageTime": 60, "step": 48, "geese": [[21, 11, 22, 23, 24, 25, 36, 37, 38, 39], [2, 1, 0, 10, 76, 65, 55, 56, 57]], "food": [75, 73], "index": 0}, "status": "ACTIVE"}, {"action": "EAST", "reward": 4909, "info": {}, "observation": {"remainingOverageTime": 60, "index": 1}, "status": "ACTIVE"}], [{"action": "WEST", "reward": 5010, "info": {}, "observation": {"remainingOverageTime": 60, "step": 49, "geese": [[20, 21, 11, 22, 23, 24, 25, 36, 37, 38], [3, 2, 1, 0, 10, 76, 65, 55, 56]], "food": [75, 73], "index": 0}, "status": "ACTIVE"}, {"action": "EAST", "reward": 5009, "info": {}, "observation": {"remainingOverageTime": 60, "index": 1}, "status": "ACTIVE"}], [{"action": "NORTH", "reward": 5110, "info": {}, "observation": {"remainingOverageTime": 60, "step": 50, "geese": [[9, 20, 21, 11, 22, 23, 24, 25, 36, 37], [4, 3, 2, 1, 0, 10, 76, 65, 55]], "food": [75, 73], "index": 0}, "status": "ACTIVE"}, {"action": "EAST", "reward": 5109, "info": {}, "observation": {"remainingOverageTime": 60, "index": 1}, "status": "ACTIVE"}], [{"action": "NORTH", "reward": 5211, "info": {}, "observation": {"remainingOverageTime": 60, "step": 51, "geese": [[75, 9, 20, 21, 11, 22, 23, 24, 25, 36, 37], [5, 4, 3, 2, 1, 0, 10, 76, 65]], "food": [73, 53], "index": 0}, "status": "ACTIVE"}, {"action": "EAST", "reward": 5209, "info": {}, "observation": {"remainingOverageTime": 60, "index": 1}, "status": "ACTIVE"}], [{"action": "WEST", "reward": 5311, "info": {}, "observation": {"remainingOverageTime": 60, "step": 52, "geese": [[74, 75, 9, 20, 21, 11, 22, 23, 24, 25, 36], [6, 5, 4, 3, 2, 1, 0, 10, 76]], "food": [73, 53], "index": 0}, "status": "ACTIVE"}, {"action": "EAST", "reward": 5309, "info": {}, "observation": {"remainingOverageTime": 60, "index": 1}, "status": "ACTIVE"}], [{"action": "WEST", "reward": 5412, "info": {}, "observation": {"remainingOverageTime": 60, "step": 53, "geese": [[73, 74, 75, 9, 20, 21, 11, 22, 23, 24, 25, 36], [72, 6, 5, 4, 3, 2, 1, 0, 10]], "food": [53, 34], "index": 0}, "status": "ACTIVE"}, {"action": "NORTH", "reward": 5409, "info": {}, "observation": {"remainingOverageTime": 60, "index": 1}, "status": "ACTIVE"}], [{"action": "NORTH", "reward": 5512, "info": {}, "observation": {"remainingOverageTime": 60, "step": 54, "geese": [[62, 73, 74, 75, 9, 20, 21, 11, 22, 23, 24, 25], [61, 72, 6, 5, 4, 3, 2, 1, 0]], "food": [53, 34], "index": 0}, "status": "ACTIVE"}, {"action": "NORTH", "reward": 5509, "info": {}, "observation": {"remainingOverageTime": 60, "index": 1}, "status": "ACTIVE"}], [{"action": "NORTH", "reward": 5612, "info": {}, "observation": {"remainingOverageTime": 60, "step": 55, "geese": [[51, 62, 73, 74, 75, 9, 20, 21, 11, 22, 23, 24], [50, 61, 72, 6, 5, 4, 3, 2, 1]], "food": [53, 34], "index": 0}, "status": "ACTIVE"}, {"action": "NORTH", "reward": 5609, "info": {}, "observation": {"remainingOverageTime": 60, "index": 1}, "status": "ACTIVE"}], [{"action": "EAST", "reward": 5712, "info": {}, "observation": {"remainingOverageTime": 60, "step": 56, "geese": [[52, 51, 62, 73, 74, 75, 9, 20, 21, 11, 22, 23], [39, 50, 61, 72, 6, 5, 4, 3, 2]], "food": [53, 34], "index": 0}, "status": "ACTIVE"}, {"action": "NORTH", "reward": 5709, "info": {}, "observation": {"remainingOverageTime": 60, "index": 1}, "status": "ACTIVE"}], [{"action": "EAST", "reward": 5813, "info": {}, "observation": {"remainingOverageTime": 60, "step": 57, "geese": [[53, 52, 51, 62, 73, 74, 75, 9, 20, 21, 11, 22, 23], [38, 39, 50, 61, 72, 6, 5, 4, 3]], "food": [34, 31], "index": 0}, "status": "ACTIVE"}, {"action": "WEST", "reward": 5809, "info": {}, "observation": {"remainingOverageTime": 60, "index": 1}, "status": "ACTIVE"}], [{"action": "EAST", "reward": 5913, "info": {}, "observation": {"remainingOverageTime": 60, "step": 58, "geese": [[54, 53, 52, 51, 62, 73, 74, 75, 9, 20, 21, 11, 22], [37, 38, 39, 50, 61, 72, 6, 5, 4]], "food": [34, 31], "index": 0}, "status": "ACTIVE"}, {"action": "WEST", "reward": 5909, "info": {}, "observation": {"remainingOverageTime": 60, "index": 1}, "status": "ACTIVE"}], [{"action": "EAST", "reward": 6013, "info": {}, "observation": {"remainingOverageTime": 60, "step": 59, "geese": [[44, 54, 53, 52, 51, 62, 73, 74, 75, 9, 20, 21, 11], [36, 37, 38, 39, 50, 61, 72, 6, 5]], "food": [34, 31], "index": 0}, "status": "ACTIVE"}, {"action": "WEST", "reward": 6009, "info": {}, "observation": {"remainingOverageTime": 60, "index": 1}, "status": "ACTIVE"}], [{"action": "EAST", "reward": 6113, "info": {}, "observation": {"remainingOverageTime": 60, "step": 60, "geese": [[45, 44, 54, 53, 52, 51, 62, 73, 74, 75, 9, 20, 21], [35, 36, 37, 38, 39, 50, 61, 72, 6]], "food": [34, 31], "index": 0}, "status": "ACTIVE"}, {"action": "WEST", "reward": 6109, "info": {}, "observation": {"remainingOverageTime": 60, "index": 1}, "status": "ACTIVE"}], [{"action": "NORTH", "reward": 6214, "info": {}, "observation": {"remainingOverageTime": 60, "step": 61, "geese": [[34, 45, 44, 54, 53, 52, 51, 62, 73, 74, 75, 9, 20, 21], [24, 35, 36, 37, 38, 39, 50, 61, 72]], "food": [31, 4], "index": 0}, "status": "ACTIVE"}, {"action": "NORTH", "reward": 6209, "info": {}, "observation": {"remainingOverageTime": 60, "index": 1}, "status": "ACTIVE"}], [{"action": "NORTH", "reward": 6314, "info": {}, "observation": {"remainingOverageTime": 60, "step": 62, "geese": [[23, 34, 45, 44, 54, 53, 52, 51, 62, 73, 74, 75, 9, 20], [25, 24, 35, 36, 37, 38, 39, 50, 61]], "food": [31, 4], "index": 0}, "status": "ACTIVE"}, {"action": "EAST", "reward": 6309, "info": {}, "observation": {"remainingOverageTime": 60, "index": 1}, "status": "ACTIVE"}], [{"action": "WEST", "reward": 6414, "info": {}, "observation": {"remainingOverageTime": 60, "step": 63, "geese": [[22, 23, 34, 45, 44, 54, 53, 52, 51, 62, 73, 74, 75, 9], [26, 25, 24, 35, 36, 37, 38, 39, 50]], "food": [31, 4], "index": 0}, "status": "ACTIVE"}, {"action": "EAST", "reward": 6409, "info": {}, "observation": {"remainingOverageTime": 60, "index": 1}, "status": "ACTIVE"}], [{"action": "WEST", "reward": 6514, "info": {}, "observation": {"remainingOverageTime": 60, "step": 64, "geese": [[32, 22, 23, 34, 45, 44, 54, 53, 52, 51, 62, 73, 74, 75], [15, 26, 25, 24, 35, 36, 37, 38, 39]], "food": [31, 4], "index": 0}, "status": "ACTIVE"}, {"action": "NORTH", "reward": 6509, "info": {}, "observation": {"remainingOverageTime": 60, "index": 1}, "status": "ACTIVE"}], [{"action": "WEST", "reward": 6615, "info": {}, "observation": {"remainingOverageTime": 60, "step": 65, "geese": [[31, 32, 22, 23, 34, 45, 44, 54, 53, 52, 51, 62, 73, 74, 75], [4, 15, 26, 25, 24, 35, 36, 37, 38, 39]], "food": [63, 67], "index": 0}, "status": "ACTIVE"}, {"action": "NORTH", "reward": 6610, "info": {}, "observation": {"remainingOverageTime": 60, "index": 1}, "status": "ACTIVE"}], [{"action": "WEST", "reward": 6715, "info": {}, "observation": {"remainingOverageTime": 60, "step": 66, "geese": [[30, 31, 32, 22, 23, 34, 45, 44, 54, 53, 52, 51, 62, 73, 74], [70, 4, 15, 26, 25, 24, 35, 36, 37, 38]], "food": [63, 67], "index": 0}, "status": "ACTIVE"}, {"action": "NORTH", "reward": 6710, "info": {}, "observation": {"remainingOverageTime": 60, "index": 1}, "status": "ACTIVE"}], [{"action": "NORTH", "reward": 6815, "info": {}, "observation": {"remainingOverageTime": 60, "step": 67, "geese": [[19, 30, 31, 32, 22, 23, 34, 45, 44, 54, 53, 52, 51, 62, 73], [69, 70, 4, 15, 26, 25, 24, 35, 36, 37]], "food": [63, 67], "index": 0}, "status": "ACTIVE"}, {"action": "WEST", "reward": 6810, "info": {}, "observation": {"remainingOverageTime": 60, "index": 1}, "status": "ACTIVE"}], [{"action": "NORTH", "reward": 6915, "info": {}, "observation": {"remainingOverageTime": 60, "step": 68, "geese": [[8, 19, 30, 31, 32, 22, 23, 34, 45, 44, 54, 53, 52, 51, 62], [68, 69, 70, 4, 15, 26, 25, 24, 35, 36]], "food": [63, 67], "index": 0}, "status": "ACTIVE"}, {"action": "WEST", "reward": 6910, "info": {}, "observation": {"remainingOverageTime": 60, "index": 1}, "status": "ACTIVE"}], [{"action": "NORTH", "reward": 7015, "info": {}, "observation": {"remainingOverageTime": 60, "step": 69, "geese": [[74, 8, 19, 30, 31, 32, 22, 23, 34, 45, 44, 54, 53, 52, 51], [67, 68, 69, 70, 4, 15, 26, 25, 24, 35, 36]], "food": [63, 20], "index": 0}, "status": "ACTIVE"}, {"action": "WEST", "reward": 7011, "info": {}, "observation": {"remainingOverageTime": 60, "index": 1}, "status": "ACTIVE"}], [{"action": "NORTH", "reward": 7116, "info": {}, "observation": {"remainingOverageTime": 60, "step": 70, "geese": [[63, 74, 8, 19, 30, 31, 32, 22, 23, 34, 45, 44, 54, 53, 52, 51], [66, 67, 68, 69, 70, 4, 15, 26, 25, 24, 35]], "food": [20, 40], "index": 0}, "status": "ACTIVE"}, {"action": "WEST", "reward": 7111, "info": {}, "observation": {"remainingOverageTime": 60, "index": 1}, "status": "ACTIVE"}], [{"action": "WEST", "reward": 7216, "info": {}, "observation": {"remainingOverageTime": 60, "step": 71, "geese": [[62, 63, 74, 8, 19, 30, 31, 32, 22, 23, 34, 45, 44, 54, 53, 52], [76, 66, 67, 68, 69, 70, 4, 15, 26, 25, 24]], "food": [20, 40], "index": 0}, "status": "ACTIVE"}, {"action": "WEST", "reward": 7211, "info": {}, "observation": {"remainingOverageTime": 60, "index": 1}, "status": "ACTIVE"}], [{"action": "NORTH", "reward": 7316, "info": {}, "observation": {"remainingOverageTime": 60, "step": 72, "geese": [[51, 62, 63, 74, 8, 19, 30, 31, 32, 22, 23, 34, 45, 44, 54, 53], [75, 76, 66, 67, 68, 69, 70, 4, 15, 26, 25]], "food": [20, 40], "index": 0}, "status": "ACTIVE"}, {"action": "WEST", "reward": 7311, "info": {}, "observation": {"remainingOverageTime": 60, "index": 1}, "status": "ACTIVE"}], [{"action": "NORTH", "reward": 7417, "info": {}, "observation": {"remainingOverageTime": 60, "step": 73, "geese": [[40, 51, 62, 63, 74, 8, 19, 30, 31, 32, 22, 23, 34, 45, 44, 54, 53], [9, 75, 76, 66, 67, 68, 69, 70, 4, 15, 26]], "food": [20, 3], "index": 0}, "status": "ACTIVE"}, {"action": "SOUTH", "reward": 7411, "info": {}, "observation": {"remainingOverageTime": 60, "index": 1}, "status": "ACTIVE"}], [{"action": "NORTH", "reward": 7517, "info": {}, "observation": {"remainingOverageTime": 60, "step": 74, "geese": [[29, 40, 51, 62, 63, 74, 8, 19, 30, 31, 32, 22, 23, 34, 45, 44, 54], [20, 9, 75, 76, 66, 67, 68, 69, 70, 4, 15, 26]], "food": [3, 6], "index": 0}, "status": "ACTIVE"}, {"action": "SOUTH", "reward": 7512, "info": {}, "observation": {"remainingOverageTime": 60, "index": 1}, "status": "ACTIVE"}], [{"action": "NORTH", "reward": 7617, "info": {}, "observation": {"remainingOverageTime": 60, "step": 75, "geese": [[18, 29, 40, 51, 62, 63, 74, 8, 19, 30, 31, 32, 22, 23, 34, 45, 44], [21, 20, 9, 75, 76, 66, 67, 68, 69, 70, 4, 15]], "food": [3, 6], "index": 0}, "status": "ACTIVE"}, {"action": "EAST", "reward": 7612, "info": {}, "observation": {"remainingOverageTime": 60, "index": 1}, "status": "ACTIVE"}], [{"action": "NORTH", "reward": 7717, "info": {}, "observation": {"remainingOverageTime": 60, "step": 76, "geese": [[7, 18, 29, 40, 51, 62, 63, 74, 8, 19, 30, 31, 32, 22, 23, 34, 45], [11, 21, 20, 9, 75, 76, 66, 67, 68, 69, 70, 4]], "food": [3, 6], "index": 0}, "status": "ACTIVE"}, {"action": "EAST", "reward": 7712, "info": {}, "observation": {"remainingOverageTime": 60, "index": 1}, "status": "ACTIVE"}], [{"action": "WEST", "reward": 7818, "info": {}, "observation": {"remainingOverageTime": 60, "step": 77, "geese": [[6, 7, 18, 29, 40, 51, 62, 63, 74, 8, 19, 30, 31, 32, 22, 23, 34, 45], [12, 11, 21, 20, 9, 75, 76, 66, 67, 68, 69, 70]], "food": [3, 56], "index": 0}, "status": "ACTIVE"}, {"action": "EAST", "reward": 7812, "info": {}, "observation": {"remainingOverageTime": 60, "index": 1}, "status": "ACTIVE"}], [{"action": "WEST", "reward": 7918, "info": {}, "observation": {"remainingOverageTime": 60, "step": 78, "geese": [[5, 6, 7, 18, 29, 40, 51, 62, 63, 74, 8, 19, 30, 31, 32, 22, 23, 34], [13, 12, 11, 21, 20, 9, 75, 76, 66, 67, 68, 69]], "food": [3, 56], "index": 0}, "status": "ACTIVE"}, {"action": "EAST", "reward": 7912, "info": {}, "observation": {"remainingOverageTime": 60, "index": 1}, "status": "ACTIVE"}], [{"action": "WEST", "reward": 8018, "info": {}, "observation": {"remainingOverageTime": 60, "step": 79, "geese": [[4, 5, 6, 7, 18, 29, 40, 51, 62, 63, 74, 8, 19, 30, 31, 32, 22, 23], [14, 13, 12, 11, 21, 20, 9, 75, 76, 66, 67, 68]], "food": [3, 56], "index": 0}, "status": "ACTIVE"}, {"action": "EAST", "reward": 8012, "info": {}, "observation": {"remainingOverageTime": 60, "index": 1}, "status": "ACTIVE"}], [{"action": "WEST", "reward": 8118, "info": {}, "observation": {"remainingOverageTime": 60, "step": 80, "geese": [[3, 4, 5, 6, 7, 18, 29, 40, 51, 62, 63, 74, 8, 19, 30, 31, 32, 22], [25, 14, 13, 12, 11, 21, 20, 9, 75, 76, 66]], "food": [56, 10], "index": 0}, "status": "ACTIVE"}, {"action": "SOUTH", "reward": 8111, "info": {}, "observation": {"remainingOverageTime": 60, "index": 1}, "status": "ACTIVE"}], [{"action": "NORTH", "reward": 8218, "info": {}, "observation": {"remainingOverageTime": 60, "step": 81, "geese": [[69, 3, 4, 5, 6, 7, 18, 29, 40, 51, 62, 63, 74, 8, 19, 30, 31, 32], [24, 25, 14, 13, 12, 11, 21, 20, 9, 75, 76]], "food": [56, 10], "index": 0}, "status": "ACTIVE"}, {"action": "WEST", "reward": 8211, "info": {}, "observation": {"remainingOverageTime": 60, "index": 1}, "status": "ACTIVE"}], [{"action": "NORTH", "reward": 8318, "info": {}, "observation": {"remainingOverageTime": 60, "step": 82, "geese": [[58, 69, 3, 4, 5, 6, 7, 18, 29, 40, 51, 62, 63, 74, 8, 19, 30, 31], [23, 24, 25, 14, 13, 12, 11, 21, 20, 9, 75]], "food": [56, 10], "index": 0}, "status": "ACTIVE"}, {"action": "WEST", "reward": 8311, "info": {}, "observation": {"remainingOverageTime": 60, "index": 1}, "status": "ACTIVE"}], [{"action": "WEST", "reward": 8418, "info": {}, "observation": {"remainingOverageTime": 60, "step": 83, "geese": [[57, 58, 69, 3, 4, 5, 6, 7, 18, 29, 40, 51, 62, 63, 74, 8, 19, 30], [34, 23, 24, 25, 14, 13, 12, 11, 21, 20, 9]], "food": [56, 10], "index": 0}, "status": "ACTIVE"}, {"action": "SOUTH", "reward": 8411, "info": {}, "observation": {"remainingOverageTime": 60, "index": 1}, "status": "ACTIVE"}], [{"action": "WEST", "reward": 8519, "info": {}, "observation": {"remainingOverageTime": 60, "step": 84, "geese": [[56, 57, 58, 69, 3, 4, 5, 6, 7, 18, 29, 40, 51, 62, 63, 74, 8, 19, 30], [33, 34, 23, 24, 25, 14, 13, 12, 11, 21, 20]], "food": [10, 71], "index": 0}, "status": "ACTIVE"}, {"action": "WEST", "reward": 8511, "info": {}, "observation": {"remainingOverageTime": 60, "index": 1}, "status": "ACTIVE"}], [{"action": "WEST", "reward": 8619, "info": {}, "observation": {"remainingOverageTime": 60, "step": 85, "geese": [[55, 56, 57, 58, 69, 3, 4, 5, 6, 7, 18, 29, 40, 51, 62, 63, 74, 8, 19], [43, 33, 34, 23, 24, 25, 14, 13, 12, 11, 21]], "food": [10, 71], "index": 0}, "status": "ACTIVE"}, {"action": "WEST", "reward": 8611, "info": {}, "observation": {"remainingOverageTime": 60, "index": 1}, "status": "ACTIVE"}], [{"action": "WEST", "reward": 8719, "info": {}, "observation": {"remainingOverageTime": 60, "step": 86, "geese": [[65, 55, 56, 57, 58, 69, 3, 4, 5, 6, 7, 18, 29, 40, 51, 62, 63, 74, 8], [32, 43, 33, 34, 23, 24, 25, 14, 13, 12, 11]], "food": [10, 71], "index": 0}, "status": "ACTIVE"}, {"action": "NORTH", "reward": 8711, "info": {}, "observation": {"remainingOverageTime": 60, "index": 1}, "status": "ACTIVE"}], [{"action": "SOUTH", "reward": 8819, "info": {}, "observation": {"remainingOverageTime": 60, "step": 87, "geese": [[76, 65, 55, 56, 57, 58, 69, 3, 4, 5, 6, 7, 18, 29, 40, 51, 62, 63, 74], [21, 32, 43, 33, 34, 23, 24, 25, 14, 13, 12]], "food": [10, 71], "index": 0}, "status": "ACTIVE"}, {"action": "NORTH", "reward": 8811, "info": {}, "observation": {"remainingOverageTime": 60, "index": 1}, "status": "ACTIVE"}], [{"action": "WEST", "reward": 8919, "info": {}, "observation": {"remainingOverageTime": 60, "step": 88, "geese": [[75, 76, 65, 55, 56, 57, 58, 69, 3, 4, 5, 6, 7, 18, 29, 40, 51, 62, 63], [20, 21, 32, 43, 33, 34, 23, 24, 25, 14, 13]], "food": [10, 71], "index": 0}, "status": "ACTIVE"}, {"action": "WEST", "reward": 8911, "info": {}, "observation": {"remainingOverageTime": 60, "index": 1}, "status": "ACTIVE"}], [{"action": "WEST", "reward": 9019, "info": {}, "observation": {"remainingOverageTime": 60, "step": 89, "geese": [[74, 75, 76, 65, 55, 56, 57, 58, 69, 3, 4, 5, 6, 7, 18, 29, 40, 51, 62], [31, 20, 21, 32, 43, 33, 34, 23, 24, 25, 14]], "food": [10, 71], "index": 0}, "status": "ACTIVE"}, {"action": "SOUTH", "reward": 9011, "info": {}, "observation": {"remainingOverageTime": 60, "index": 1}, "status": "ACTIVE"}], [{"action": "WEST", "reward": 9119, "info": {}, "observation": {"remainingOverageTime": 60, "step": 90, "geese": [[73, 74, 75, 76, 65, 55, 56, 57, 58, 69, 3, 4, 5, 6, 7, 18, 29, 40, 51], [42, 31, 20, 21, 32, 43, 33, 34, 23, 24, 25]], "food": [10, 71], "index": 0}, "status": "ACTIVE"}, {"action": "SOUTH", "reward": 9111, "info": {}, "observation": {"remainingOverageTime": 60, "index": 1}, "status": "ACTIVE"}], [{"action": "WEST", "reward": 9219, "info": {}, "observation": {"remainingOverageTime": 60, "step": 91, "geese": [[72, 73, 74, 75, 76, 65, 55, 56, 57, 58, 69, 3, 4, 5, 6, 7, 18, 29, 40], [41, 42, 31, 20, 21, 32, 43, 33, 34, 23, 24]], "food": [10, 71], "index": 0}, "status": "ACTIVE"}, {"action": "WEST", "reward": 9211, "info": {}, "observation": {"remainingOverageTime": 60, "index": 1}, "status": "ACTIVE"}], [{"action": "WEST", "reward": 9320, "info": {}, "observation": {"remainingOverageTime": 60, "step": 92, "geese": [[71, 72, 73, 74, 75, 76, 65, 55, 56, 57, 58, 69, 3, 4, 5, 6, 7, 18, 29, 40], [30, 41, 42, 31, 20, 21, 32, 43, 33, 34, 23]], "food": [10, 48], "index": 0}, "status": "ACTIVE"}, {"action": "NORTH", "reward": 9311, "info": {}, "observation": {"remainingOverageTime": 60, "index": 1}, "status": "ACTIVE"}], [{"action": "NORTH", "reward": 9420, "info": {}, "observation": {"remainingOverageTime": 60, "step": 93, "geese": [[60, 71, 72, 73, 74, 75, 76, 65, 55, 56, 57, 58, 69, 3, 4, 5, 6, 7, 18, 29], [19, 30, 41, 42, 31, 20, 21, 32, 43, 33, 34]], "food": [10, 48], "index": 0}, "status": "ACTIVE"}, {"action": "NORTH", "reward": 9411, "info": {}, "observation": {"remainingOverageTime": 60, "index": 1}, "status": "ACTIVE"}], [{"action": "NORTH", "reward": 9520, "info": {}, "observation": {"remainingOverageTime": 60, "step": 94, "geese": [[49, 60, 71, 72, 73, 74, 75, 76, 65, 55, 56, 57, 58, 69, 3, 4, 5, 6, 7, 18], [8, 19, 30, 41, 42, 31, 20, 21, 32, 43, 33]], "food": [10, 48], "index": 0}, "status": "ACTIVE"}, {"action": "NORTH", "reward": 9511, "info": {}, "observation": {"remainingOverageTime": 60, "index": 1}, "status": "ACTIVE"}], [{"action": "WEST", "reward": 9621, "info": {}, "observation": {"remainingOverageTime": 60, "step": 95, "geese": [[48, 49, 60, 71, 72, 73, 74, 75, 76, 65, 55, 56, 57, 58, 69, 3, 4, 5, 6, 7, 18], [9, 8, 19, 30, 41, 42, 31, 20, 21, 32, 43]], "food": [10, 22], "index": 0}, "status": "ACTIVE"}, {"action": "EAST", "reward": 9611, "info": {}, "observation": {"remainingOverageTime": 60, "index": 1}, "status": "ACTIVE"}], [{"action": "WEST", "reward": 9721, "info": {}, "observation": {"remainingOverageTime": 60, "step": 96, "geese": [[47, 48, 49, 60, 71, 72, 73, 74, 75, 76, 65, 55, 56, 57, 58, 69, 3, 4, 5, 6, 7], [10, 9, 8, 19, 30, 41, 42, 31, 20, 21, 32, 43]], "food": [22, 63], "index": 0}, "status": "ACTIVE"}, {"action": "EAST", "reward": 9712, "info": {}, "observation": {"remainingOverageTime": 60, "index": 1}, "status": "ACTIVE"}], [{"action": "WEST", "reward": 9821, "info": {}, "observation": {"remainingOverageTime": 60, "step": 97, "geese": [[46, 47, 48, 49, 60, 71, 72, 73, 74, 75, 76, 65, 55, 56, 57, 58, 69, 3, 4, 5, 6], [0, 10, 9, 8, 19, 30, 41, 42, 31, 20, 21, 32]], "food": [22, 63], "index": 0}, "status": "ACTIVE"}, {"action": "EAST", "reward": 9812, "info": {}, "observation": {"remainingOverageTime": 60, "index": 1}, "status": "ACTIVE"}], [{"action": "WEST", "reward": 9921, "info": {}, "observation": {"remainingOverageTime": 60, "step": 98, "geese": [[45, 46, 47, 48, 49, 60, 71, 72, 73, 74, 75, 76, 65, 55, 56, 57, 58, 69, 3, 4, 5], [11, 0, 10, 9, 8, 19, 30, 41, 42, 31, 20, 21]], "food": [22, 63], "index": 0}, "status": "ACTIVE"}, {"action": "SOUTH", "reward": 9912, "info": {}, "observation": {"remainingOverageTime": 60, "index": 1}, "status": "ACTIVE"}], [{"action": "WEST", "reward": 10021, "info": {}, "observation": {"remainingOverageTime": 60, "step": 99, "geese": [[44, 45, 46, 47, 48, 49, 60, 71, 72, 73, 74, 75, 76, 65, 55, 56, 57, 58, 69, 3, 4], [22, 11, 0, 10, 9, 8, 19, 30, 41, 42, 31, 20, 21]], "food": [63, 50], "index": 0}, "status": "ACTIVE"}, {"action": "SOUTH", "reward": 10013, "info": {}, "observation": {"remainingOverageTime": 60, "index": 1}, "status": "ACTIVE"}], [{"action": "WEST", "reward": 10121, "info": {}, "observation": {"remainingOverageTime": 60, "step": 100, "geese": [[54, 44, 45, 46, 47, 48, 49, 60, 71, 72, 73, 74, 75, 76, 65, 55, 56, 57, 58, 69, 3], [23, 22, 11, 0, 10, 9, 8, 19, 30, 41, 42, 31, 20]], "food": [63, 50], "index": 0}, "status": "ACTIVE"}, {"action": "EAST", "reward": 10113, "info": {}, "observation": {"remainingOverageTime": 60, "index": 1}, "status": "ACTIVE"}], [{"action": "WEST", "reward": 10221, "info": {}, "observation": {"remainingOverageTime": 60, "step": 101, "geese": [[53, 54, 44, 45, 46, 47, 48, 49, 60, 71, 72, 73, 74, 75, 76, 65, 55, 56, 57, 58, 69], [24, 23, 22, 11, 0, 10, 9, 8, 19, 30, 41, 42, 31]], "food": [63, 50], "index": 0}, "status": "ACTIVE"}, {"action": "EAST", "reward": 10213, "info": {}, "observation": {"remainingOverageTime": 60, "index": 1}, "status": "ACTIVE"}], [{"action": "SOUTH", "reward": 10321, "info": {}, "observation": {"remainingOverageTime": 60, "step": 102, "geese": [[64, 53, 54, 44, 45, 46, 47, 48, 49, 60, 71, 72, 73, 74, 75, 76, 65, 55, 56, 57, 58], [25, 24, 23, 22, 11, 0, 10, 9, 8, 19, 30, 41, 42]], "food": [63, 50], "index": 0}, "status": "ACTIVE"}, {"action": "EAST", "reward": 10313, "info": {}, "observation": {"remainingOverageTime": 60, "index": 1}, "status": "ACTIVE"}], [{"action": "WEST", "reward": 10422, "info": {}, "observation": {"remainingOverageTime": 60, "step": 103, "geese": [[63, 64, 53, 54, 44, 45, 46, 47, 48, 49, 60, 71, 72, 73, 74, 75, 76, 65, 55, 56, 57, 58], [26, 25, 24, 23, 22, 11, 0, 10, 9, 8, 19, 30, 41]], "food": [50, 37], "index": 0}, "status": "ACTIVE"}, {"action": "EAST", "reward": 10413, "info": {}, "observation": {"remainingOverageTime": 60, "index": 1}, "status": "ACTIVE"}], [{"action": "WEST", "reward": 10522, "info": {}, "observation": {"remainingOverageTime": 60, "step": 104, "geese": [[62, 63, 64, 53, 54, 44, 45, 46, 47, 48, 49, 60, 71, 72, 73, 74, 75, 76, 65, 55, 56, 57], [37, 26, 25, 24, 23, 22, 11, 0, 10, 9, 8, 19, 30, 41]], "food": [50, 68], "index": 0}, "status": "ACTIVE"}, {"action": "SOUTH", "reward": 10514, "info": {}, "observation": {"remainingOverageTime": 60, "index": 1}, "status": "ACTIVE"}], [{"action": "WEST", "reward": 10622, "info": {}, "observation": {"remainingOverageTime": 60, "step": 105, "geese": [[61, 62, 63, 64, 53, 54, 44, 45, 46, 47, 48, 49, 60, 71, 72, 73, 74, 75, 76, 65, 55, 56], [38, 37, 26, 25, 24, 23, 22, 11, 0, 10, 9, 8, 19, 30]], "food": [50, 68], "index": 0}, "status": "ACTIVE"}, {"action": "EAST", "reward": 10614, "info": {}, "observation": {"remainingOverageTime": 60, "index": 1}, "status": "ACTIVE"}], [{"action": "NORTH", "reward": 10723, "info": {}, "observation": {"remainingOverageTime": 60, "step": 106, "geese": [[50, 61, 62, 63, 64, 53, 54, 44, 45, 46, 47, 48, 49, 60, 71, 72, 73, 74, 75, 76, 65, 55, 56], [27, 38, 37, 26, 25, 24, 23, 22, 11, 0, 10, 9, 8, 19]], "food": [68, 21], "index": 0}, "status": "ACTIVE"}, {"action": "NORTH", "reward": 10714, "info": {}, "observation": {"remainingOverageTime": 60, "index": 1}, "status": "ACTIVE"}], [{"action": "NORTH", "reward": 10823, "info": {}, "observation": {"remainingOverageTime": 60, "step": 107, "geese": [[39, 50, 61, 62, 63, 64, 53, 54, 44, 45, 46, 47, 48, 49, 60, 71, 72, 73, 74, 75, 76, 65, 55], [28, 27, 38, 37, 26, 25, 24, 23, 22, 11, 0, 10, 9, 8]], "food": [68, 21], "index": 0}, "status": "ACTIVE"}, {"action": "EAST", "reward": 10814, "info": {}, "observation": {"remainingOverageTime": 60, "index": 1}, "status": "ACTIVE"}], [{"action": "EAST", "reward": 10923, "info": {}, "observation": {"remainingOverageTime": 60, "step": 108, "geese": [[40, 39, 50, 61, 62, 63, 64, 53, 54, 44, 45, 46, 47, 48, 49, 60, 71, 72, 73, 74, 75, 76, 65], [29, 28, 27, 38, 37, 26, 25, 24, 23, 22, 11, 0, 10, 9]], "food": [68, 21], "index": 0}, "status": "ACTIVE"}, {"action": "EAST", "reward": 10914, "info": {}, "observation": {"remainingOverageTime": 60, "index": 1}, "status": "ACTIVE"}], [{"action": "EAST", "reward": 11023, "info": {}, "observation": {"remainingOverageTime": 60, "step": 109, "geese": [[41, 40, 39, 50, 61, 62, 63, 64, 53, 54, 44, 45, 46, 47, 48, 49, 60, 71, 72, 73, 74, 75, 76], [30, 29, 28, 27, 38, 37, 26, 25, 24, 23, 22, 11, 0, 10]], "food": [68, 21], "index": 0}, "status": "ACTIVE"}, {"action": "EAST", "reward": 11014, "info": {}, "observation": {"remainingOverageTime": 60, "index": 1}, "status": "ACTIVE"}], [{"action": "EAST", "reward": 11123, "info": {}, "observation": {"remainingOverageTime": 60, "step": 110, "geese": [[42, 41, 40, 39, 50, 61, 62, 63, 64, 53, 54, 44, 45, 46, 47, 48, 49, 60, 71, 72, 73, 74, 75], [31, 30, 29, 28, 27, 38, 37, 26, 25, 24, 23, 22, 11, 0]], "food": [68, 21], "index": 0}, "status": "ACTIVE"}, {"action": "EAST", "reward": 11114, "info": {}, "observation": {"remainingOverageTime": 60, "index": 1}, "status": "ACTIVE"}], [{"action": "EAST", "reward": 11223, "info": {}, "observation": {"remainingOverageTime": 60, "step": 111, "geese": [[43, 42, 41, 40, 39, 50, 61, 62, 63, 64, 53, 54, 44, 45, 46, 47, 48, 49, 60, 71, 72, 73, 74], [32, 31, 30, 29, 28, 27, 38, 37, 26, 25, 24, 23, 22, 11]], "food": [68, 21], "index": 0}, "status": "ACTIVE"}, {"action": "EAST", "reward": 11214, "info": {}, "observation": {"remainingOverageTime": 60, "index": 1}, "status": "ACTIVE"}], [{"action": "EAST", "reward": 11323, "info": {}, "observation": {"remainingOverageTime": 60, "step": 112, "geese": [[33, 43, 42, 41, 40, 39, 50, 61, 62, 63, 64, 53, 54, 44, 45, 46, 47, 48, 49, 60, 71, 72, 73], [21, 32, 31, 30, 29, 28, 27, 38, 37, 26, 25, 24, 23, 22, 11]], "food": [68, 4], "index": 0}, "status": "ACTIVE"}, {"action": "NORTH", "reward": 11315, "info": {}, "observation": {"remainingOverageTime": 60, "index": 1}, "status": "ACTIVE"}], [{"action": "EAST", "reward": 11423, "info": {}, "observation": {"remainingOverageTime": 60, "step": 113, "geese": [[34, 33, 43, 42, 41, 40, 39, 50, 61, 62, 63, 64, 53, 54, 44, 45, 46, 47, 48, 49, 60, 71, 72], [11, 21, 32, 31, 30, 29, 28, 27, 38, 37, 26, 25, 24, 23, 22]], "food": [68, 4], "index": 0}, "status": "ACTIVE"}, {"action": "EAST", "reward": 11415, "info": {}, "observation": {"remainingOverageTime": 60, "index": 1}, "status": "ACTIVE"}], [{"action": "EAST", "reward": 11523, "info": {}, "observation": {"remainingOverageTime": 60, "step": 114, "geese": [[35, 34, 33, 43, 42, 41, 40, 39, 50, 61, 62, 63, 64, 53, 54, 44, 45, 46, 47, 48, 49, 60, 71], [12, 11, 21, 32, 31, 30, 29, 28, 27, 38, 37, 26, 25, 24, 23]], "food": [68, 4], "index": 0}, "status": "ACTIVE"}, {"action": "EAST", "reward": 11515, "info": {}, "observation": {"remainingOverageTime": 60, "index": 1}, "status": "ACTIVE"}], [{"action": "EAST", "reward": 11623, "info": {}, "observation": {"remainingOverageTime": 60, "step": 115, "geese": [[36, 35, 34, 33, 43, 42, 41, 40, 39, 50, 61, 62, 63, 64, 53, 54, 44, 45, 46, 47, 48, 49, 60], [13, 12, 11, 21, 32, 31, 30, 29, 28, 27, 38, 37, 26, 25, 24]], "food": [68, 4], "index": 0}, "status": "ACTIVE"}, {"action": "EAST", "reward": 11615, "info": {}, "observation": {"remainingOverageTime": 60, "index": 1}, "status": "ACTIVE"}], [{"action": "EAST", "reward": 11623, "info": {}, "observation": {"remainingOverageTime": 60, "step": 116, "geese": [[], [2, 13, 12, 11, 21, 32, 31, 30, 29, 28, 27, 38, 37, 26, 25]], "food": [68, 4], "index": 0}, "status": "DONE"}, {"action": "NORTH", "reward": 11715, "info": {}, "observation": {"remainingOverageTime": 60, "index": 1}, "status": "DONE"}]], "rewards": [11623, 11715], "statuses": ["DONE", "DONE"], "schema_version": 1, "info": {}}